{
		"type":"object",
		"$schema": "http://json-schema.org/draft-04/hyper-schema",
		"name": "mail detail",
		"description": "mail detail",
		"id": "mail:v2",
		"properties":{
				"mail_number":{
						"type":"long",
						"description": "mail number"
				},
				"mail_link":{
						"type":"string",
						"description": "mail link"
				},
				"sender":{
						"type":"string",
						"description": "sender id"
				},
				"nick":{
						"type":"string",
						"description": "sender id"
				},
				"title":{
						"type":"string",
						"description": "sender id"
				},
				"date":{
						"type":"string",
						"description": "sender id"
				},
				"source":{
						"type":"string",
						"description": "sender id"
				},
				"ip":{
						"type":"string",
						"description": "sender id"
				},
				"is_new":{
						"type":"boolean",
						"description": "if the mail is new"
				},
				"mark_sign":{
						"type":"string",
						"description": "mark sign"
				},
				"content":{
						"type":"string",
						"description": "mail content in html format"
				}
		}
}
